{
    "miniprogramRoot": "dist/",
    "projectname": "guanggu-forum-app",
    "description": "光谷过早客论坛 app",
    "appid": "wx7d4ca3252ddf79a3",
    "setting": {
        "urlCheck": true,
        "es6": false,
        "enhance": false,
        "compileHotReLoad": false,
        "postcss": false,
        "minified": false,
        "babelSetting": {
            "ignore": [],
            "disablePlugins": [],
            "outputPath": ""
        }
    },
    "compileType": "miniprogram",
    "libVersion": "2.25.2",
    "srcMiniprogramRoot": "dist/",
    "packOptions": {
        "ignore": [],
        "include": []
    },
    "condition": {},
    "editorSetting": {
        "tabIndent": "insertSpaces",
        "tabSize": 4
    }
}